{
  "entries": [
    {
      "column": 14,
      "fingerprint": "39c756661128d749ee90c613",
      "line": 52,
      "message": "High-entropy string literal detected.",
      "path": "docs/artifacts/day25-community-pack/day25-community-summary.json",
      "rule_id": "SEC_HIGH_ENTROPY_STRING",
      "severity": "warn",
      "suggestion": ""
    },
    {
      "column": 14,
      "fingerprint": "2074db91e077dcef2e3c6651",
      "line": 52,
      "message": "High-entropy string literal detected.",
      "path": "docs/artifacts/day26-external-contribution-pack/day26-external-contribution-summary.json",
      "rule_id": "SEC_HIGH_ENTROPY_STRING",
      "severity": "warn",
      "suggestion": ""
    },
    {
      "column": 14,
      "fingerprint": "8df29f4c590bda35be9c79c9",
      "line": 52,
      "message": "High-entropy string literal detected.",
      "path": "docs/artifacts/day27-kpi-pack/day27-kpi-summary.json",
      "rule_id": "SEC_HIGH_ENTROPY_STRING",
      "severity": "warn",
      "suggestion": ""
    },
    {
      "column": 14,
      "fingerprint": "ded4de2c866dbb42ace0ad3d",
      "line": 53,
      "message": "High-entropy string literal detected.",
      "path": "docs/artifacts/day28-weekly-pack/day28-weekly-review-summary.json",
      "rule_id": "SEC_HIGH_ENTROPY_STRING",
      "severity": "warn",
      "suggestion": ""
    },
    {
      "column": 14,
      "fingerprint": "71ef4bf996bfb1b0fdc51ab2",
      "line": 44,
      "message": "High-entropy string literal detected.",
      "path": "docs/artifacts/day29-hardening-pack/day29-phase1-hardening-summary.json",
      "rule_id": "SEC_HIGH_ENTROPY_STRING",
      "severity": "warn",
      "suggestion": ""
    },
    {
      "column": 19,
      "fingerprint": "606debf20f573ccde7968a14",
      "line": 65,
      "message": "High-entropy string literal detected.",
      "path": "docs/artifacts/day31-phase2-pack/day31-phase2-kickoff-summary.json",
      "rule_id": "SEC_HIGH_ENTROPY_STRING",
      "severity": "warn",
      "suggestion": ""
    },
    {
      "column": 19,
      "fingerprint": "f617a525e1070502df3d05e6",
      "line": 81,
      "message": "High-entropy string literal detected.",
      "path": "docs/artifacts/day31-phase2-pack/day31-phase2-kickoff-summary.json",
      "rule_id": "SEC_HIGH_ENTROPY_STRING",
      "severity": "warn",
      "suggestion": ""
    },
    {
      "column": 19,
      "fingerprint": "e3e852cb7d6416b910c0dc62",
      "line": 53,
      "message": "High-entropy string literal detected.",
      "path": "docs/artifacts/day32-release-cadence-pack/day32-release-cadence-summary.json",
      "rule_id": "SEC_HIGH_ENTROPY_STRING",
      "severity": "warn",
      "suggestion": ""
    },
    {
      "column": 19,
      "fingerprint": "5d84066b840c057d38bb0b68",
      "line": 53,
      "message": "High-entropy string literal detected.",
      "path": "docs/artifacts/day34-demo-asset2-pack/day34-demo-asset2-summary.json",
      "rule_id": "SEC_HIGH_ENTROPY_STRING",
      "severity": "warn",
      "suggestion": ""
    },
    {
      "column": 19,
      "fingerprint": "9ae9f4256dff1bdca5009829",
      "line": 53,
      "message": "High-entropy string literal detected.",
      "path": "docs/artifacts/day35-kpi-instrumentation-pack/day35-kpi-instrumentation-summary.json",
      "rule_id": "SEC_HIGH_ENTROPY_STRING",
      "severity": "warn",
      "suggestion": ""
    },
    {
      "column": 19,
      "fingerprint": "0a36a58249c19423c7eed019",
      "line": 53,
      "message": "High-entropy string literal detected.",
      "path": "docs/artifacts/day36-distribution-closeout-pack/day36-distribution-closeout-summary.json",
      "rule_id": "SEC_HIGH_ENTROPY_STRING",
      "severity": "warn",
      "suggestion": ""
    },
    {
      "column": 19,
      "fingerprint": "d559847ed1c9539f1fe77d03",
      "line": 53,
      "message": "High-entropy string literal detected.",
      "path": "docs/artifacts/day37-experiment-lane-pack/day37-experiment-lane-summary.json",
      "rule_id": "SEC_HIGH_ENTROPY_STRING",
      "severity": "warn",
      "suggestion": ""
    },
    {
      "column": 19,
      "fingerprint": "4b52502bd99eadf98c9d4dde",
      "line": 99,
      "message": "High-entropy string literal detected.",
      "path": "docs/artifacts/day37-experiment-lane-pack/day37-experiment-lane-summary.json",
      "rule_id": "SEC_HIGH_ENTROPY_STRING",
      "severity": "warn",
      "suggestion": ""
    },
    {
      "column": 19,
      "fingerprint": "613aa2a2731a7d1c289f8da2",
      "line": 53,
      "message": "High-entropy string literal detected.",
      "path": "docs/artifacts/day38-distribution-batch-pack/day38-distribution-batch-summary.json",
      "rule_id": "SEC_HIGH_ENTROPY_STRING",
      "severity": "warn",
      "suggestion": ""
    },
    {
      "column": 19,
      "fingerprint": "00b45f5e0a8f6e659b4561ce",
      "line": 53,
      "message": "High-entropy string literal detected.",
      "path": "docs/artifacts/day39-playbook-post-pack/day39-playbook-post-summary.json",
      "rule_id": "SEC_HIGH_ENTROPY_STRING",
      "severity": "warn",
      "suggestion": ""
    },
    {
      "column": 19,
      "fingerprint": "c94aeac046c496c68774bf1c",
      "line": 99,
      "message": "High-entropy string literal detected.",
      "path": "docs/artifacts/day41-expansion-automation-pack/day41-expansion-automation-summary.json",
      "rule_id": "SEC_HIGH_ENTROPY_STRING",
      "severity": "warn",
      "suggestion": ""
    },
    {
      "column": 19,
      "fingerprint": "901b01fe4b2eb192a5805adc",
      "line": 53,
      "message": "High-entropy string literal detected.",
      "path": "docs/artifacts/day42-optimization-closeout-pack/day42-optimization-closeout-summary.json",
      "rule_id": "SEC_HIGH_ENTROPY_STRING",
      "severity": "warn",
      "suggestion": ""
    },
    {
      "column": 19,
      "fingerprint": "f558d2e8eb3aa9431f264628",
      "line": 99,
      "message": "High-entropy string literal detected.",
      "path": "docs/artifacts/day42-optimization-closeout-pack/day42-optimization-closeout-summary.json",
      "rule_id": "SEC_HIGH_ENTROPY_STRING",
      "severity": "warn",
      "suggestion": ""
    },
    {
      "column": 19,
      "fingerprint": "e3aef6094842306c729d2eb2",
      "line": 53,
      "message": "High-entropy string literal detected.",
      "path": "docs/artifacts/day45-expansion-closeout-pack/day45-expansion-closeout-summary.json",
      "rule_id": "SEC_HIGH_ENTROPY_STRING",
      "severity": "warn",
      "suggestion": ""
    },
    {
      "column": 19,
      "fingerprint": "25b678fc2210b7310cbafe57",
      "line": 99,
      "message": "High-entropy string literal detected.",
      "path": "docs/artifacts/day45-expansion-closeout-pack/day45-expansion-closeout-summary.json",
      "rule_id": "SEC_HIGH_ENTROPY_STRING",
      "severity": "warn",
      "suggestion": ""
    },
    {
      "column": 19,
      "fingerprint": "16aa1acc7235bc1bc49db350",
      "line": 53,
      "message": "High-entropy string literal detected.",
      "path": "docs/artifacts/day46-optimization-closeout-pack/day46-optimization-closeout-summary.json",
      "rule_id": "SEC_HIGH_ENTROPY_STRING",
      "severity": "warn",
      "suggestion": ""
    },
    {
      "column": 19,
      "fingerprint": "dc394ebede6184005f950f58",
      "line": 99,
      "message": "High-entropy string literal detected.",
      "path": "docs/artifacts/day46-optimization-closeout-pack/day46-optimization-closeout-summary.json",
      "rule_id": "SEC_HIGH_ENTROPY_STRING",
      "severity": "warn",
      "suggestion": ""
    },
    {
      "column": 19,
      "fingerprint": "7c3e91521c637393b9add547",
      "line": 53,
      "message": "High-entropy string literal detected.",
      "path": "docs/artifacts/day47-reliability-closeout-pack/day47-reliability-closeout-summary.json",
      "rule_id": "SEC_HIGH_ENTROPY_STRING",
      "severity": "warn",
      "suggestion": ""
    },
    {
      "column": 19,
      "fingerprint": "75d524d2d4518e533dcde75a",
      "line": 53,
      "message": "High-entropy string literal detected.",
      "path": "docs/artifacts/day48-objection-closeout-pack/day48-objection-closeout-summary.json",
      "rule_id": "SEC_HIGH_ENTROPY_STRING",
      "severity": "warn",
      "suggestion": ""
    },
    {
      "column": 19,
      "fingerprint": "eeccf6a64cda69d6ce7b907e",
      "line": 53,
      "message": "High-entropy string literal detected.",
      "path": "docs/artifacts/day49-weekly-review-closeout-pack/day49-weekly-review-closeout-summary.json",
      "rule_id": "SEC_HIGH_ENTROPY_STRING",
      "severity": "warn",
      "suggestion": ""
    },
    {
      "column": 19,
      "fingerprint": "dc2585728b6ae40ea065a758",
      "line": 99,
      "message": "High-entropy string literal detected.",
      "path": "docs/artifacts/day50-execution-prioritization-closeout-pack/day50-execution-prioritization-closeout-summary.json",
      "rule_id": "SEC_HIGH_ENTROPY_STRING",
      "severity": "warn",
      "suggestion": ""
    },
    {
      "column": 19,
      "fingerprint": "aaee97bf5766ace342990a49",
      "line": 53,
      "message": "High-entropy string literal detected.",
      "path": "docs/artifacts/day52-narrative-closeout-pack/day52-narrative-closeout-summary.json",
      "rule_id": "SEC_HIGH_ENTROPY_STRING",
      "severity": "warn",
      "suggestion": ""
    },
    {
      "column": 19,
      "fingerprint": "084c65d9db2d21f586b5617a",
      "line": 53,
      "message": "High-entropy string literal detected.",
      "path": "docs/artifacts/day53-docs-loop-closeout-pack/day53-docs-loop-closeout-summary.json",
      "rule_id": "SEC_HIGH_ENTROPY_STRING",
      "severity": "warn",
      "suggestion": ""
    },
    {
      "column": 21,
      "fingerprint": "b1ff18475feee18ecb596857",
      "line": 116,
      "message": "High-entropy string literal detected.",
      "path": "src/sdetkit/community_activation.py",
      "rule_id": "SEC_HIGH_ENTROPY_STRING",
      "severity": "warn",
      "suggestion": ""
    },
    {
      "column": 5,
      "fingerprint": "bf05cabe865530ecd9a85059",
      "line": 135,
      "message": "High-entropy string literal detected.",
      "path": "src/sdetkit/community_activation.py",
      "rule_id": "SEC_HIGH_ENTROPY_STRING",
      "severity": "warn",
      "suggestion": ""
    },
    {
      "column": 8,
      "fingerprint": "12760a5ae8f62cb6e950d916",
      "line": 443,
      "message": "print(...) found in src/.",
      "path": "src/sdetkit/community_activation.py",
      "rule_id": "SEC_DEBUG_PRINT",
      "severity": "info",
      "suggestion": ""
    },
    {
      "column": 8,
      "fingerprint": "930351d024542773fc01ca86",
      "line": 445,
      "message": "print(...) found in src/.",
      "path": "src/sdetkit/community_activation.py",
      "rule_id": "SEC_DEBUG_PRINT",
      "severity": "info",
      "suggestion": ""
    },
    {
      "column": 25,
      "fingerprint": "938311efdf5fe088b080d54a",
      "line": 159,
      "message": "High-entropy string literal detected.",
      "path": "src/sdetkit/day28_weekly_review.py",
      "rule_id": "SEC_HIGH_ENTROPY_STRING",
      "severity": "warn",
      "suggestion": ""
    },
    {
      "column": 9,
      "fingerprint": "3b89bbef4a6346de7b64c0ad",
      "line": 200,
      "message": "High-entropy string literal detected.",
      "path": "src/sdetkit/day28_weekly_review.py",
      "rule_id": "SEC_HIGH_ENTROPY_STRING",
      "severity": "warn",
      "suggestion": ""
    },
    {
      "column": 8,
      "fingerprint": "e3182322969fa4f8156107fb",
      "line": 421,
      "message": "print(...) found in src/.",
      "path": "src/sdetkit/day28_weekly_review.py",
      "rule_id": "SEC_DEBUG_PRINT",
      "severity": "info",
      "suggestion": ""
    },
    {
      "column": 25,
      "fingerprint": "3d8b39bb9f37f4c680d5e4bb",
      "line": 155,
      "message": "High-entropy string literal detected.",
      "path": "src/sdetkit/day29_phase1_hardening.py",
      "rule_id": "SEC_HIGH_ENTROPY_STRING",
      "severity": "warn",
      "suggestion": ""
    },
    {
      "column": 8,
      "fingerprint": "3152b04f48934c211e80361d",
      "line": 336,
      "message": "print(...) found in src/.",
      "path": "src/sdetkit/day29_phase1_hardening.py",
      "rule_id": "SEC_DEBUG_PRINT",
      "severity": "info",
      "suggestion": ""
    },
    {
      "column": 8,
      "fingerprint": "6a7a202df7f4d9657cf85aa0",
      "line": 429,
      "message": "print(...) found in src/.",
      "path": "src/sdetkit/day30_phase1_wrap.py",
      "rule_id": "SEC_DEBUG_PRINT",
      "severity": "info",
      "suggestion": ""
    },
    {
      "column": 25,
      "fingerprint": "da9caa6becd175091a950bbc",
      "line": 222,
      "message": "High-entropy string literal detected.",
      "path": "src/sdetkit/day31_phase2_kickoff.py",
      "rule_id": "SEC_HIGH_ENTROPY_STRING",
      "severity": "warn",
      "suggestion": ""
    },
    {
      "column": 25,
      "fingerprint": "cc5d9da6517468ec23e7e15b",
      "line": 238,
      "message": "High-entropy string literal detected.",
      "path": "src/sdetkit/day31_phase2_kickoff.py",
      "rule_id": "SEC_HIGH_ENTROPY_STRING",
      "severity": "warn",
      "suggestion": ""
    },
    {
      "column": 8,
      "fingerprint": "a5ae7ff14e400bf7a55024a2",
      "line": 493,
      "message": "print(...) found in src/.",
      "path": "src/sdetkit/day31_phase2_kickoff.py",
      "rule_id": "SEC_DEBUG_PRINT",
      "severity": "info",
      "suggestion": ""
    },
    {
      "column": 25,
      "fingerprint": "4988223ba603219e088996c9",
      "line": 222,
      "message": "High-entropy string literal detected.",
      "path": "src/sdetkit/day32_release_cadence.py",
      "rule_id": "SEC_HIGH_ENTROPY_STRING",
      "severity": "warn",
      "suggestion": ""
    },
    {
      "column": 8,
      "fingerprint": "ba021f1d2d2521e89dbb99dd",
      "line": 523,
      "message": "print(...) found in src/.",
      "path": "src/sdetkit/day32_release_cadence.py",
      "rule_id": "SEC_DEBUG_PRINT",
      "severity": "info",
      "suggestion": ""
    },
    {
      "column": 8,
      "fingerprint": "2974807cb087d96562c174fb",
      "line": 514,
      "message": "print(...) found in src/.",
      "path": "src/sdetkit/day33_demo_asset.py",
      "rule_id": "SEC_DEBUG_PRINT",
      "severity": "info",
      "suggestion": ""
    },
    {
      "column": 25,
      "fingerprint": "049550a615fdb224f07139c3",
      "line": 222,
      "message": "High-entropy string literal detected.",
      "path": "src/sdetkit/day34_demo_asset2.py",
      "rule_id": "SEC_HIGH_ENTROPY_STRING",
      "severity": "warn",
      "suggestion": ""
    },
    {
      "column": 8,
      "fingerprint": "ca62a32f607cb8a9503a9d2c",
      "line": 516,
      "message": "print(...) found in src/.",
      "path": "src/sdetkit/day34_demo_asset2.py",
      "rule_id": "SEC_DEBUG_PRINT",
      "severity": "info",
      "suggestion": ""
    },
    {
      "column": 25,
      "fingerprint": "d9436d47b0f3aa64ff53f609",
      "line": 222,
      "message": "High-entropy string literal detected.",
      "path": "src/sdetkit/day35_kpi_instrumentation.py",
      "rule_id": "SEC_HIGH_ENTROPY_STRING",
      "severity": "warn",
      "suggestion": ""
    },
    {
      "column": 8,
      "fingerprint": "40a873c09fd254f9780668c7",
      "line": 510,
      "message": "print(...) found in src/.",
      "path": "src/sdetkit/day35_kpi_instrumentation.py",
      "rule_id": "SEC_DEBUG_PRINT",
      "severity": "info",
      "suggestion": ""
    },
    {
      "column": 25,
      "fingerprint": "a0b116ec0f99595aa35e99aa",
      "line": 224,
      "message": "High-entropy string literal detected.",
      "path": "src/sdetkit/day36_distribution_closeout.py",
      "rule_id": "SEC_HIGH_ENTROPY_STRING",
      "severity": "warn",
      "suggestion": ""
    },
    {
      "column": 8,
      "fingerprint": "8fe5da3ec8d32d9e6f1a609d",
      "line": 525,
      "message": "print(...) found in src/.",
      "path": "src/sdetkit/day36_distribution_closeout.py",
      "rule_id": "SEC_DEBUG_PRINT",
      "severity": "info",
      "suggestion": ""
    },
    {
      "column": 25,
      "fingerprint": "16eb1c9126915d2085fcd773",
      "line": 224,
      "message": "High-entropy string literal detected.",
      "path": "src/sdetkit/day37_experiment_lane.py",
      "rule_id": "SEC_HIGH_ENTROPY_STRING",
      "severity": "warn",
      "suggestion": ""
    },
    {
      "column": 25,
      "fingerprint": "76fdcf4df0420500044d1137",
      "line": 268,
      "message": "High-entropy string literal detected.",
      "path": "src/sdetkit/day37_experiment_lane.py",
      "rule_id": "SEC_HIGH_ENTROPY_STRING",
      "severity": "warn",
      "suggestion": ""
    },
    {
      "column": 8,
      "fingerprint": "5916b67d83a8877fc4c39657",
      "line": 554,
      "message": "print(...) found in src/.",
      "path": "src/sdetkit/day37_experiment_lane.py",
      "rule_id": "SEC_DEBUG_PRINT",
      "severity": "info",
      "suggestion": ""
    },
    {
      "column": 25,
      "fingerprint": "7cbfb8298e7c24254fee6bc7",
      "line": 222,
      "message": "High-entropy string literal detected.",
      "path": "src/sdetkit/day38_distribution_batch.py",
      "rule_id": "SEC_HIGH_ENTROPY_STRING",
      "severity": "warn",
      "suggestion": ""
    },
    {
      "column": 8,
      "fingerprint": "6d3220bf2e5c202bf44470ae",
      "line": 554,
      "message": "print(...) found in src/.",
      "path": "src/sdetkit/day38_distribution_batch.py",
      "rule_id": "SEC_DEBUG_PRINT",
      "severity": "info",
      "suggestion": ""
    },
    {
      "column": 25,
      "fingerprint": "1ffef8e73e587085ddb5eafa",
      "line": 224,
      "message": "High-entropy string literal detected.",
      "path": "src/sdetkit/day39_playbook_post.py",
      "rule_id": "SEC_HIGH_ENTROPY_STRING",
      "severity": "warn",
      "suggestion": ""
    },
    {
      "column": 8,
      "fingerprint": "5baff612a18d3a310169a2ab",
      "line": 548,
      "message": "print(...) found in src/.",
      "path": "src/sdetkit/day39_playbook_post.py",
      "rule_id": "SEC_DEBUG_PRINT",
      "severity": "info",
      "suggestion": ""
    },
    {
      "column": 8,
      "fingerprint": "1607947608c30fbd0e13a150",
      "line": 544,
      "message": "print(...) found in src/.",
      "path": "src/sdetkit/day40_scale_lane.py",
      "rule_id": "SEC_DEBUG_PRINT",
      "severity": "info",
      "suggestion": ""
    },
    {
      "column": 25,
      "fingerprint": "040a3ddbdf7a0c5dbc5f6ef2",
      "line": 261,
      "message": "High-entropy string literal detected.",
      "path": "src/sdetkit/day41_expansion_automation.py",
      "rule_id": "SEC_HIGH_ENTROPY_STRING",
      "severity": "warn",
      "suggestion": ""
    },
    {
      "column": 8,
      "fingerprint": "696ee89f865147c81f57b833",
      "line": 546,
      "message": "print(...) found in src/.",
      "path": "src/sdetkit/day41_expansion_automation.py",
      "rule_id": "SEC_DEBUG_PRINT",
      "severity": "info",
      "suggestion": ""
    },
    {
      "column": 25,
      "fingerprint": "dcb3e42332b3708d633940aa",
      "line": 219,
      "message": "High-entropy string literal detected.",
      "path": "src/sdetkit/day42_optimization_closeout.py",
      "rule_id": "SEC_HIGH_ENTROPY_STRING",
      "severity": "warn",
      "suggestion": ""
    },
    {
      "column": 25,
      "fingerprint": "51bf2baa6786b78e745e26ca",
      "line": 263,
      "message": "High-entropy string literal detected.",
      "path": "src/sdetkit/day42_optimization_closeout.py",
      "rule_id": "SEC_HIGH_ENTROPY_STRING",
      "severity": "warn",
      "suggestion": ""
    },
    {
      "column": 8,
      "fingerprint": "a52602f7162ae80c80c45be3",
      "line": 487,
      "message": "print(...) found in src/.",
      "path": "src/sdetkit/day42_optimization_closeout.py",
      "rule_id": "SEC_DEBUG_PRINT",
      "severity": "info",
      "suggestion": ""
    },
    {
      "column": 8,
      "fingerprint": "ca052a052a1fdc0ef86965de",
      "line": 489,
      "message": "print(...) found in src/.",
      "path": "src/sdetkit/day42_optimization_closeout.py",
      "rule_id": "SEC_DEBUG_PRINT",
      "severity": "info",
      "suggestion": ""
    },
    {
      "column": 25,
      "fingerprint": "67580bc2934fc91dcd086529",
      "line": 219,
      "message": "High-entropy string literal detected.",
      "path": "src/sdetkit/day43_acceleration_closeout.py",
      "rule_id": "SEC_HIGH_ENTROPY_STRING",
      "severity": "warn",
      "suggestion": ""
    },
    {
      "column": 8,
      "fingerprint": "faa3dbec93fb7cc64ed88cc4",
      "line": 487,
      "message": "print(...) found in src/.",
      "path": "src/sdetkit/day43_acceleration_closeout.py",
      "rule_id": "SEC_DEBUG_PRINT",
      "severity": "info",
      "suggestion": ""
    },
    {
      "column": 8,
      "fingerprint": "ab50442c072a9e351438b723",
      "line": 489,
      "message": "print(...) found in src/.",
      "path": "src/sdetkit/day43_acceleration_closeout.py",
      "rule_id": "SEC_DEBUG_PRINT",
      "severity": "info",
      "suggestion": ""
    },
    {
      "column": 8,
      "fingerprint": "dedfcbff341d1e001f3c2166",
      "line": 481,
      "message": "print(...) found in src/.",
      "path": "src/sdetkit/day44_scale_closeout.py",
      "rule_id": "SEC_DEBUG_PRINT",
      "severity": "info",
      "suggestion": ""
    },
    {
      "column": 8,
      "fingerprint": "6ce3c31e32e773303dccdcba",
      "line": 483,
      "message": "print(...) found in src/.",
      "path": "src/sdetkit/day44_scale_closeout.py",
      "rule_id": "SEC_DEBUG_PRINT",
      "severity": "info",
      "suggestion": ""
    },
    {
      "column": 25,
      "fingerprint": "f27d157f178ee17c2cace761",
      "line": 217,
      "message": "High-entropy string literal detected.",
      "path": "src/sdetkit/day45_expansion_closeout.py",
      "rule_id": "SEC_HIGH_ENTROPY_STRING",
      "severity": "warn",
      "suggestion": ""
    },
    {
      "column": 25,
      "fingerprint": "70f6ae2ededdd671e6a6abda",
      "line": 261,
      "message": "High-entropy string literal detected.",
      "path": "src/sdetkit/day45_expansion_closeout.py",
      "rule_id": "SEC_HIGH_ENTROPY_STRING",
      "severity": "warn",
      "suggestion": ""
    },
    {
      "column": 8,
      "fingerprint": "1be5f5232ed7398dafa2601b",
      "line": 483,
      "message": "print(...) found in src/.",
      "path": "src/sdetkit/day45_expansion_closeout.py",
      "rule_id": "SEC_DEBUG_PRINT",
      "severity": "info",
      "suggestion": ""
    },
    {
      "column": 8,
      "fingerprint": "063e68a075983f0fa1cb4c57",
      "line": 485,
      "message": "print(...) found in src/.",
      "path": "src/sdetkit/day45_expansion_closeout.py",
      "rule_id": "SEC_DEBUG_PRINT",
      "severity": "info",
      "suggestion": ""
    },
    {
      "column": 25,
      "fingerprint": "0478cd4ecd7524a6e84817ab",
      "line": 218,
      "message": "High-entropy string literal detected.",
      "path": "src/sdetkit/day46_optimization_closeout.py",
      "rule_id": "SEC_HIGH_ENTROPY_STRING",
      "severity": "warn",
      "suggestion": ""
    },
    {
      "column": 25,
      "fingerprint": "cf4d8975a21739ef301a1816",
      "line": 262,
      "message": "High-entropy string literal detected.",
      "path": "src/sdetkit/day46_optimization_closeout.py",
      "rule_id": "SEC_HIGH_ENTROPY_STRING",
      "severity": "warn",
      "suggestion": ""
    },
    {
      "column": 8,
      "fingerprint": "032ede7cf709f530c385c110",
      "line": 486,
      "message": "print(...) found in src/.",
      "path": "src/sdetkit/day46_optimization_closeout.py",
      "rule_id": "SEC_DEBUG_PRINT",
      "severity": "info",
      "suggestion": ""
    },
    {
      "column": 8,
      "fingerprint": "cfd3658b8da3ad617e71f2b7",
      "line": 488,
      "message": "print(...) found in src/.",
      "path": "src/sdetkit/day46_optimization_closeout.py",
      "rule_id": "SEC_DEBUG_PRINT",
      "severity": "info",
      "suggestion": ""
    },
    {
      "column": 25,
      "fingerprint": "263f0820f3c52ebadb576f19",
      "line": 218,
      "message": "High-entropy string literal detected.",
      "path": "src/sdetkit/day47_reliability_closeout.py",
      "rule_id": "SEC_HIGH_ENTROPY_STRING",
      "severity": "warn",
      "suggestion": ""
    },
    {
      "column": 8,
      "fingerprint": "1d3e202b284288524d198724",
      "line": 484,
      "message": "print(...) found in src/.",
      "path": "src/sdetkit/day47_reliability_closeout.py",
      "rule_id": "SEC_DEBUG_PRINT",
      "severity": "info",
      "suggestion": ""
    },
    {
      "column": 8,
      "fingerprint": "31f91b238617c38209f9a1c6",
      "line": 486,
      "message": "print(...) found in src/.",
      "path": "src/sdetkit/day47_reliability_closeout.py",
      "rule_id": "SEC_DEBUG_PRINT",
      "severity": "info",
      "suggestion": ""
    },
    {
      "column": 25,
      "fingerprint": "a5211c7245209327577345d5",
      "line": 218,
      "message": "High-entropy string literal detected.",
      "path": "src/sdetkit/day48_objection_closeout.py",
      "rule_id": "SEC_HIGH_ENTROPY_STRING",
      "severity": "warn",
      "suggestion": ""
    },
    {
      "column": 8,
      "fingerprint": "06742b0bb9bfb9e242a07afe",
      "line": 484,
      "message": "print(...) found in src/.",
      "path": "src/sdetkit/day48_objection_closeout.py",
      "rule_id": "SEC_DEBUG_PRINT",
      "severity": "info",
      "suggestion": ""
    },
    {
      "column": 8,
      "fingerprint": "b496f3bef899744d1746534d",
      "line": 486,
      "message": "print(...) found in src/.",
      "path": "src/sdetkit/day48_objection_closeout.py",
      "rule_id": "SEC_DEBUG_PRINT",
      "severity": "info",
      "suggestion": ""
    },
    {
      "column": 25,
      "fingerprint": "48f51b8fab80ac9696e3d1f9",
      "line": 218,
      "message": "High-entropy string literal detected.",
      "path": "src/sdetkit/day49_weekly_review_closeout.py",
      "rule_id": "SEC_HIGH_ENTROPY_STRING",
      "severity": "warn",
      "suggestion": ""
    },
    {
      "column": 8,
      "fingerprint": "874501f780a76ac968632515",
      "line": 486,
      "message": "print(...) found in src/.",
      "path": "src/sdetkit/day49_weekly_review_closeout.py",
      "rule_id": "SEC_DEBUG_PRINT",
      "severity": "info",
      "suggestion": ""
    },
    {
      "column": 8,
      "fingerprint": "59db866cced4604e4d4d3df4",
      "line": 488,
      "message": "print(...) found in src/.",
      "path": "src/sdetkit/day49_weekly_review_closeout.py",
      "rule_id": "SEC_DEBUG_PRINT",
      "severity": "info",
      "suggestion": ""
    },
    {
      "column": 25,
      "fingerprint": "205e2511216f6bf883d709ad",
      "line": 266,
      "message": "High-entropy string literal detected.",
      "path": "src/sdetkit/day50_execution_prioritization_closeout.py",
      "rule_id": "SEC_HIGH_ENTROPY_STRING",
      "severity": "warn",
      "suggestion": ""
    },
    {
      "column": 8,
      "fingerprint": "3c45a225c209866b57bcd5c2",
      "line": 493,
      "message": "print(...) found in src/.",
      "path": "src/sdetkit/day50_execution_prioritization_closeout.py",
      "rule_id": "SEC_DEBUG_PRINT",
      "severity": "info",
      "suggestion": ""
    },
    {
      "column": 8,
      "fingerprint": "fd6997dd6eb3d23adeca60f7",
      "line": 495,
      "message": "print(...) found in src/.",
      "path": "src/sdetkit/day50_execution_prioritization_closeout.py",
      "rule_id": "SEC_DEBUG_PRINT",
      "severity": "info",
      "suggestion": ""
    },
    {
      "column": 8,
      "fingerprint": "e47bb8e4dfdcb95cd41ff1ce",
      "line": 488,
      "message": "print(...) found in src/.",
      "path": "src/sdetkit/day51_case_snippet_closeout.py",
      "rule_id": "SEC_DEBUG_PRINT",
      "severity": "info",
      "suggestion": ""
    },
    {
      "column": 8,
      "fingerprint": "2ee4e2724793172d69d35ed8",
      "line": 490,
      "message": "print(...) found in src/.",
      "path": "src/sdetkit/day51_case_snippet_closeout.py",
      "rule_id": "SEC_DEBUG_PRINT",
      "severity": "info",
      "suggestion": ""
    },
    {
      "column": 25,
      "fingerprint": "7f2c3c0c8ff4706ead239e54",
      "line": 222,
      "message": "High-entropy string literal detected.",
      "path": "src/sdetkit/day52_narrative_closeout.py",
      "rule_id": "SEC_HIGH_ENTROPY_STRING",
      "severity": "warn",
      "suggestion": ""
    },
    {
      "column": 8,
      "fingerprint": "7aa217d0c3f638321d3e117e",
      "line": 486,
      "message": "print(...) found in src/.",
      "path": "src/sdetkit/day52_narrative_closeout.py",
      "rule_id": "SEC_DEBUG_PRINT",
      "severity": "info",
      "suggestion": ""
    },
    {
      "column": 8,
      "fingerprint": "43680752b3a478624b4609f8",
      "line": 488,
      "message": "print(...) found in src/.",
      "path": "src/sdetkit/day52_narrative_closeout.py",
      "rule_id": "SEC_DEBUG_PRINT",
      "severity": "info",
      "suggestion": ""
    },
    {
      "column": 25,
      "fingerprint": "9bb95dd6ec1222d8224b9ae5",
      "line": 222,
      "message": "High-entropy string literal detected.",
      "path": "src/sdetkit/day53_docs_loop_closeout.py",
      "rule_id": "SEC_HIGH_ENTROPY_STRING",
      "severity": "warn",
      "suggestion": ""
    },
    {
      "column": 8,
      "fingerprint": "e3873f5c287199c88eaa4a9f",
      "line": 486,
      "message": "print(...) found in src/.",
      "path": "src/sdetkit/day53_docs_loop_closeout.py",
      "rule_id": "SEC_DEBUG_PRINT",
      "severity": "info",
      "suggestion": ""
    },
    {
      "column": 8,
      "fingerprint": "49258dcd8eb7b050de4f2415",
      "line": 488,
      "message": "print(...) found in src/.",
      "path": "src/sdetkit/day53_docs_loop_closeout.py",
      "rule_id": "SEC_DEBUG_PRINT",
      "severity": "info",
      "suggestion": ""
    },
    {
      "column": 4,
      "fingerprint": "dce5990b7db844bc0839aa32",
      "line": 440,
      "message": "print(...) found in src/.",
      "path": "src/sdetkit/day55_contributor_activation_closeout.py",
      "rule_id": "SEC_DEBUG_PRINT",
      "severity": "info",
      "suggestion": ""
    },
    {
      "column": 25,
      "fingerprint": "646e30fa0c2772df2d8eec69",
      "line": 218,
      "message": "High-entropy string literal detected.",
      "path": "src/sdetkit/day56_stabilization_closeout.py",
      "rule_id": "SEC_HIGH_ENTROPY_STRING",
      "severity": "warn",
      "suggestion": ""
    },
    {
      "column": 4,
      "fingerprint": "4248e9fd1c2f37a7b5b36612",
      "line": 434,
      "message": "print(...) found in src/.",
      "path": "src/sdetkit/day56_stabilization_closeout.py",
      "rule_id": "SEC_DEBUG_PRINT",
      "severity": "info",
      "suggestion": ""
    },
    {
      "column": 25,
      "fingerprint": "eed19af63ea48a65331292b4",
      "line": 211,
      "message": "High-entropy string literal detected.",
      "path": "src/sdetkit/day57_kpi_deep_audit_closeout.py",
      "rule_id": "SEC_HIGH_ENTROPY_STRING",
      "severity": "warn",
      "suggestion": ""
    },
    {
      "column": 4,
      "fingerprint": "5831267290a3d41d94757211",
      "line": 425,
      "message": "print(...) found in src/.",
      "path": "src/sdetkit/day57_kpi_deep_audit_closeout.py",
      "rule_id": "SEC_DEBUG_PRINT",
      "severity": "info",
      "suggestion": ""
    },
    {
      "column": 25,
      "fingerprint": "3056a0342c05f6efd6f1d9aa",
      "line": 193,
      "message": "High-entropy string literal detected.",
      "path": "src/sdetkit/day58_phase2_hardening_closeout.py",
      "rule_id": "SEC_HIGH_ENTROPY_STRING",
      "severity": "warn",
      "suggestion": ""
    },
    {
      "column": 4,
      "fingerprint": "2408ca0e60090efcaf71a5f8",
      "line": 426,
      "message": "print(...) found in src/.",
      "path": "src/sdetkit/day58_phase2_hardening_closeout.py",
      "rule_id": "SEC_DEBUG_PRINT",
      "severity": "info",
      "suggestion": ""
    },
    {
      "column": 25,
      "fingerprint": "24444b68e0d25109976d88a3",
      "line": 182,
      "message": "High-entropy string literal detected.",
      "path": "src/sdetkit/day59_phase3_preplan_closeout.py",
      "rule_id": "SEC_HIGH_ENTROPY_STRING",
      "severity": "warn",
      "suggestion": ""
    },
    {
      "column": 4,
      "fingerprint": "39c1c5b3e47893b3e0d4c07b",
      "line": 414,
      "message": "print(...) found in src/.",
      "path": "src/sdetkit/day59_phase3_preplan_closeout.py",
      "rule_id": "SEC_DEBUG_PRINT",
      "severity": "info",
      "suggestion": ""
    },
    {
      "column": 4,
      "fingerprint": "d6ca6e1893479ca5d1c663e6",
      "line": 419,
      "message": "print(...) found in src/.",
      "path": "src/sdetkit/day60_phase2_wrap_handoff_closeout.py",
      "rule_id": "SEC_DEBUG_PRINT",
      "severity": "info",
      "suggestion": ""
    },
    {
      "column": 21,
      "fingerprint": "0b0bda38d724935d21b197e3",
      "line": 116,
      "message": "High-entropy string literal detected.",
      "path": "src/sdetkit/external_contribution_push.py",
      "rule_id": "SEC_HIGH_ENTROPY_STRING",
      "severity": "warn",
      "suggestion": ""
    },
    {
      "column": 5,
      "fingerprint": "a180e27336ec6dce0e5fd945",
      "line": 142,
      "message": "High-entropy string literal detected.",
      "path": "src/sdetkit/external_contribution_push.py",
      "rule_id": "SEC_HIGH_ENTROPY_STRING",
      "severity": "warn",
      "suggestion": ""
    },
    {
      "column": 8,
      "fingerprint": "b620048784ea4fa14809a296",
      "line": 441,
      "message": "print(...) found in src/.",
      "path": "src/sdetkit/external_contribution_push.py",
      "rule_id": "SEC_DEBUG_PRINT",
      "severity": "info",
      "suggestion": ""
    },
    {
      "column": 8,
      "fingerprint": "1d2b7675db49a8b21cf4383e",
      "line": 443,
      "message": "print(...) found in src/.",
      "path": "src/sdetkit/external_contribution_push.py",
      "rule_id": "SEC_DEBUG_PRINT",
      "severity": "info",
      "suggestion": ""
    },
    {
      "column": 8,
      "fingerprint": "67f975cfba0f3d3a842a0b7a",
      "line": 516,
      "message": "print(...) found in src/.",
      "path": "src/sdetkit/faq_objections.py",
      "rule_id": "SEC_DEBUG_PRINT",
      "severity": "info",
      "suggestion": ""
    },
    {
      "column": 25,
      "fingerprint": "a6ee98a6382d5127752be5b6",
      "line": 203,
      "message": "High-entropy string literal detected.",
      "path": "src/sdetkit/kpi_audit.py",
      "rule_id": "SEC_HIGH_ENTROPY_STRING",
      "severity": "warn",
      "suggestion": ""
    },
    {
      "column": 9,
      "fingerprint": "0c0e20ed0973e605ac134948",
      "line": 245,
      "message": "High-entropy string literal detected.",
      "path": "src/sdetkit/kpi_audit.py",
      "rule_id": "SEC_HIGH_ENTROPY_STRING",
      "severity": "warn",
      "suggestion": ""
    },
    {
      "column": 8,
      "fingerprint": "8ae4ded9ef70745b5f2af1cc",
      "line": 488,
      "message": "print(...) found in src/.",
      "path": "src/sdetkit/kpi_audit.py",
      "rule_id": "SEC_DEBUG_PRINT",
      "severity": "info",
      "suggestion": ""
    },
    {
      "column": 8,
      "fingerprint": "d10364ad6dd6d58695cf8a83",
      "line": 490,
      "message": "print(...) found in src/.",
      "path": "src/sdetkit/kpi_audit.py",
      "rule_id": "SEC_DEBUG_PRINT",
      "severity": "info",
      "suggestion": ""
    },
    {
      "column": 8,
      "fingerprint": "3d4f7a612fa4cc818fb32f70",
      "line": 436,
      "message": "print(...) found in src/.",
      "path": "src/sdetkit/onboarding_time_upgrade.py",
      "rule_id": "SEC_DEBUG_PRINT",
      "severity": "info",
      "suggestion": ""
    },
    {
      "column": 8,
      "fingerprint": "41ad340e737395f898cc2ebd",
      "line": 438,
      "message": "print(...) found in src/.",
      "path": "src/sdetkit/onboarding_time_upgrade.py",
      "rule_id": "SEC_DEBUG_PRINT",
      "severity": "info",
      "suggestion": ""
    },
    {
      "column": 8,
      "fingerprint": "b6688cf3ca33e69e85eff0ae",
      "line": 1062,
      "message": "print(...) found in src/.",
      "path": "src/sdetkit/premium_gate_engine.py",
      "rule_id": "SEC_DEBUG_PRINT",
      "severity": "info",
      "suggestion": ""
    },
    {
      "column": 8,
      "fingerprint": "73d25e67dfd1239174f9bf85",
      "line": 1064,
      "message": "print(...) found in src/.",
      "path": "src/sdetkit/premium_gate_engine.py",
      "rule_id": "SEC_DEBUG_PRINT",
      "severity": "info",
      "suggestion": ""
    },
    {
      "column": 8,
      "fingerprint": "e662995eaa7660406b17e290",
      "line": 1066,
      "message": "print(...) found in src/.",
      "path": "src/sdetkit/premium_gate_engine.py",
      "rule_id": "SEC_DEBUG_PRINT",
      "severity": "info",
      "suggestion": ""
    },
    {
      "column": 4,
      "fingerprint": "1e3346dc4b842e15b11b85cd",
      "line": 206,
      "message": "print(...) found in src/.",
      "path": "src/sdetkit/proof.py",
      "rule_id": "SEC_DEBUG_PRINT",
      "severity": "info",
      "suggestion": ""
    },
    {
      "column": 8,
      "fingerprint": "36d709ac3717a2fa3de1b5cf",
      "line": 349,
      "message": "print(...) found in src/.",
      "path": "src/sdetkit/quality_contribution_delta.py",
      "rule_id": "SEC_DEBUG_PRINT",
      "severity": "info",
      "suggestion": ""
    },
    {
      "column": 8,
      "fingerprint": "9fe16343c6a3330a20674819",
      "line": 457,
      "message": "print(...) found in src/.",
      "path": "src/sdetkit/release_narrative.py",
      "rule_id": "SEC_DEBUG_PRINT",
      "severity": "info",
      "suggestion": ""
    },
    {
      "column": 8,
      "fingerprint": "a840662697adef6d6d87a3d6",
      "line": 400,
      "message": "print(...) found in src/.",
      "path": "src/sdetkit/release_readiness_board.py",
      "rule_id": "SEC_DEBUG_PRINT",
      "severity": "info",
      "suggestion": ""
    },
    {
      "column": 8,
      "fingerprint": "bada77e54397cd0d4eb56b53",
      "line": 399,
      "message": "print(...) found in src/.",
      "path": "src/sdetkit/reliability_evidence_pack.py",
      "rule_id": "SEC_DEBUG_PRINT",
      "severity": "info",
      "suggestion": ""
    },
    {
      "column": 8,
      "fingerprint": "0f1eac5b484e6c19a1b8848c",
      "line": 457,
      "message": "print(...) found in src/.",
      "path": "src/sdetkit/reliability_evidence_pack.py",
      "rule_id": "SEC_DEBUG_PRINT",
      "severity": "info",
      "suggestion": ""
    },
    {
      "column": 4,
      "fingerprint": "b0e2d49c2c72e041e675f732",
      "line": 329,
      "message": "print(...) found in src/.",
      "path": "src/sdetkit/startup_use_case.py",
      "rule_id": "SEC_DEBUG_PRINT",
      "severity": "info",
      "suggestion": ""
    },
    {
      "column": 4,
      "fingerprint": "376bbe0354d99e0c4a96d192",
      "line": 432,
      "message": "print(...) found in src/.",
      "path": "src/sdetkit/triage_templates.py",
      "rule_id": "SEC_DEBUG_PRINT",
      "severity": "info",
      "suggestion": ""
    },
    {
      "column": 8,
      "fingerprint": "2ef5191eca55d6fb74e369af",
      "line": 507,
      "message": "print(...) found in src/.",
      "path": "src/sdetkit/trust_signal_upgrade.py",
      "rule_id": "SEC_DEBUG_PRINT",
      "severity": "info",
      "suggestion": ""
    },
    {
      "column": 8,
      "fingerprint": "e7da4685e2ebe73770daa995",
      "line": 608,
      "message": "print(...) found in src/.",
      "path": "src/sdetkit/weekly_review.py",
      "rule_id": "SEC_DEBUG_PRINT",
      "severity": "info",
      "suggestion": ""
    }
  ]
}
